django_attachments/CHANGELOG.md
django_attachments/__init__.py
django_attachments/admin.py
django_attachments/apps.py
django_attachments/cleanup.py
django_attachments/fields.py
django_attachments/forms.py
django_attachments/models.py
django_attachments/tests.py
django_attachments/utils.py
django_attachments/views.py
django_attachments/widgets.py
django_attachments/locale/sk_SK/LC_MESSAGES/django.mo
django_attachments/locale/sk_SK/LC_MESSAGES/django.po
django_attachments/migrations/0001_initial.py
django_attachments/migrations/0002_auto_20180727_0804.py
django_attachments/migrations/0003_attachment_options.py
django_attachments/migrations/0004_rename_attachment_library_rank_django_atta_library_9d0164_idx.py
django_attachments/migrations/__init__.py
django_attachments/static/django_attachments/css/attachments.css
django_attachments/static/django_attachments/img/.gitattributes
django_attachments/static/django_attachments/img/trashcan.png
django_attachments/static/django_attachments/img/upload.png
django_attachments/static/django_attachments/img/mimetypes/application/octet-stream.png
django_attachments/static/django_attachments/img/mimetypes/application/octet-stream.svg
django_attachments/static/django_attachments/img/mimetypes/application/pdf.png
django_attachments/static/django_attachments/img/mimetypes/application/pdf.svg
django_attachments/static/django_attachments/js/admin_attachments.js
django_attachments/static/django_attachments/js/attachments.js
django_attachments/static/django_attachments/vendor/dropzone/LICENSE
django_attachments/static/django_attachments/vendor/dropzone/basic.min.css
django_attachments/static/django_attachments/vendor/dropzone/dropzone.min.css
django_attachments/static/django_attachments/vendor/dropzone/dropzone.min.js
django_attachments/static/django_attachments/vendor/sortable/LICENSE
django_attachments/static/django_attachments/vendor/sortable/Sortable.min.js
django_attachments/templates/admin/attachments/library_create.html
django_attachments_management-1.2.4.dist-info/AUTHORS
django_attachments_management-1.2.4.dist-info/LICENSE
django_attachments_management-1.2.4.dist-info/METADATA
django_attachments_management-1.2.4.dist-info/WHEEL
django_attachments_management-1.2.4.dist-info/top_level.txt
django_attachments_management-1.2.4.dist-info/RECORD
