Metadata-Version: 2.1
Name: django_attachments_management
Version: 1.2.4
Summary: Attachments management app for django
Author-email: Miroslav Bendík <miroslav.bendik@gmail.com>
License: MIT
Project-URL: homepage, https://github.com/mireq/django-attachments
Project-URL: documentation, https://github.com/mireq/django-attachments
Project-URL: repository, https://github.com/mireq/django-attachments
Project-URL: changelog, https://github.com/mireq/django-attachments/blob/master/CHANGELOG.md
Keywords: pylibmc,django
Classifier: Programming Language :: Python :: 3
Requires-Python: >=3.7
License-File: LICENSE
License-File: AUTHORS
Requires-Dist: django
Requires-Dist: easy_thumbnails
Provides-Extra: dev
Requires-Dist: pylint; extra == "dev"
Requires-Dist: pre-commit; extra == "dev"
Requires-Dist: bump2version; extra == "dev"
Requires-Dist: commitizen; extra == "dev"
